lowerpines/__init__.py
lowerpines/bot.py
lowerpines/chat.py
lowerpines/exceptions.py
lowerpines/gmi.py
lowerpines/group.py
lowerpines/manager.py
lowerpines/message.py
lowerpines/py.typed
lowerpines/user.py
lowerpines/endpoints/__init__.py
lowerpines/endpoints/block.py
lowerpines/endpoints/bot.py
lowerpines/endpoints/chat.py
lowerpines/endpoints/group.py
lowerpines/endpoints/image.py
lowerpines/endpoints/leaderboard.py
lowerpines/endpoints/like.py
lowerpines/endpoints/member.py
lowerpines/endpoints/message.py
lowerpines/endpoints/object.py
lowerpines/endpoints/request.py
lowerpines/endpoints/sms.py
lowerpines/endpoints/user.py
lowerpines-0.6.0.dist-info/LICENSE.txt
lowerpines-0.6.0.dist-info/METADATA
lowerpines-0.6.0.dist-info/WHEEL
lowerpines-0.6.0.dist-info/top_level.txt
lowerpines-0.6.0.dist-info/RECORD
