Metadata-Version: 2.1
Name: lowerpines
Version: 0.6.0
Summary: Library wrapper for GroupMe API
Home-page: https://github.com/bigfootjon/lowerpines
Author: Jonathan Janzen
Author-email: jjjonjanzen@gmail.com
License: GNU Lesser General Public License v3 (LGPLv3)
Download-URL: https://github.com/bigfootjon/lowerpines/tarball/0.6.0
Keywords: api,GroupMe
Platform: UNKNOWN
Classifier: Development Status :: 4 - Beta
Classifier: Operating System :: OS Independent
Classifier: Topic :: Communications :: Chat
Classifier: Topic :: Internet
Classifier: Intended Audience :: Developers
Classifier: License :: OSI Approved :: GNU Lesser General Public License v3 (LGPLv3)
Classifier: Natural Language :: English
Classifier: Programming Language :: Python
Classifier: Programming Language :: Python :: 3
Classifier: Programming Language :: Python :: 3.6
Classifier: Programming Language :: Python :: 3.7
Classifier: Programming Language :: Python :: 3.8
Classifier: Programming Language :: Python :: 3 :: Only
Classifier: Typing :: Typed
Requires-Python: >=3.6
Requires-Dist: requests
